<?xml version="1.0" encoding="UTF-8"?>
<!DOCTYPE mapper PUBLIC "-//mybatis.org//DTD Mapper 3.0//EN" "http://mybatis.org/dtd/mybatis-3-mapper.dtd">
<mapper namespace="com.i9he.m2b.mapper.JDPayMapper">
  <resultMap id="BaseResultMap" type="com.i9he.m2b.model.JDPay">
    <!--
      WARNING - @mbggenerated
      This element is automatically generated by MyBatis Generator, do not modify.
      copyright@ www.9he.com
    -->
    <id column="id" jdbcType="INTEGER" property="id" />
    <result column="create_user_id" jdbcType="INTEGER" property="createUserId" />
    <result column="create_time" jdbcType="TIMESTAMP" property="createTime" />
    <result column="type" jdbcType="TINYINT" property="type" />
    <result column="order_id" jdbcType="VARCHAR" property="orderId" />
    <result column="pay_state" jdbcType="TINYINT" property="payState" />
    <result column="end_time" jdbcType="TIMESTAMP" property="endTime" />
    <result column="total_fee" jdbcType="DECIMAL" property="totalFee" />
    <result column="v_oid" jdbcType="VARCHAR" property="vOid" />
    <result column="v_pmodeid" jdbcType="VARCHAR" property="vPmodeid" />
    <result column="v_pmode" jdbcType="VARCHAR" property="vPmode" />
    <result column="v_pstatus" jdbcType="VARCHAR" property="vPstatus" />
    <result column="v_pstring" jdbcType="VARCHAR" property="vPstring" />
    <result column="v_amount" jdbcType="VARCHAR" property="vAmount" />
    <result column="v_moneytype" jdbcType="VARCHAR" property="vMoneytype" />
    <result column="remark1" jdbcType="VARCHAR" property="remark1" />
    <result column="remark2" jdbcType="VARCHAR" property="remark2" />
  </resultMap>
  <sql id="Base_Column_List">
    <!--
      WARNING - @mbggenerated
      This element is automatically generated by MyBatis Generator, do not modify.
      copyright@ www.9he.com
    -->
    id, create_user_id, create_time, `type`, order_id, pay_state, end_time, total_fee, 
    v_oid, v_pmodeid, v_pmode, v_pstatus, v_pstring, v_amount, v_moneytype, remark1, 
    remark2
  </sql>
  <select id="selectByPrimaryKey" parameterType="java.lang.Integer" resultMap="BaseResultMap">
    <!--
      WARNING - @mbggenerated
      This element is automatically generated by MyBatis Generator, do not modify.
      copyright@ www.9he.com
    -->
    select 
    <include refid="Base_Column_List" />
    from b2b_pay_jdpay
    where id = #{id,jdbcType=INTEGER}
  </select>
  <insert id="insert" keyProperty="id" parameterType="com.i9he.m2b.model.JDPay" useGeneratedKeys="true">
    <!--
      WARNING - @mbggenerated
      This element is automatically generated by MyBatis Generator, do not modify.
      copyright@ www.9he.com
    -->
    insert into b2b_pay_jdpay (create_user_id, create_time, `type`, 
      order_id, pay_state, end_time, 
      total_fee, v_oid, v_pmodeid, 
      v_pmode, v_pstatus, v_pstring, 
      v_amount, v_moneytype, remark1, 
      remark2)
    values (#{createUserId,jdbcType=INTEGER}, #{createTime,jdbcType=TIMESTAMP}, #{type,jdbcType=TINYINT}, 
      #{orderId,jdbcType=VARCHAR}, #{payState,jdbcType=TINYINT}, #{endTime,jdbcType=TIMESTAMP}, 
      #{totalFee,jdbcType=DECIMAL}, #{vOid,jdbcType=VARCHAR}, #{vPmodeid,jdbcType=VARCHAR}, 
      #{vPmode,jdbcType=VARCHAR}, #{vPstatus,jdbcType=VARCHAR}, #{vPstring,jdbcType=VARCHAR}, 
      #{vAmount,jdbcType=VARCHAR}, #{vMoneytype,jdbcType=VARCHAR}, #{remark1,jdbcType=VARCHAR}, 
      #{remark2,jdbcType=VARCHAR})
  </insert>
  <insert id="insertSelective" keyProperty="id" parameterType="com.i9he.m2b.model.JDPay" useGeneratedKeys="true">
    <!--
      WARNING - @mbggenerated
      This element is automatically generated by MyBatis Generator, do not modify.
      copyright@ www.9he.com
    -->
    insert into b2b_pay_jdpay
    <trim prefix="(" suffix=")" suffixOverrides=",">
      <if test="createUserId != null">
        create_user_id,
      </if>
      <if test="createTime != null">
        create_time,
      </if>
      <if test="type != null">
        `type`,
      </if>
      <if test="orderId != null">
        order_id,
      </if>
      <if test="payState != null">
        pay_state,
      </if>
      <if test="endTime != null">
        end_time,
      </if>
      <if test="totalFee != null">
        total_fee,
      </if>
      <if test="vOid != null">
        v_oid,
      </if>
      <if test="vPmodeid != null">
        v_pmodeid,
      </if>
      <if test="vPmode != null">
        v_pmode,
      </if>
      <if test="vPstatus != null">
        v_pstatus,
      </if>
      <if test="vPstring != null">
        v_pstring,
      </if>
      <if test="vAmount != null">
        v_amount,
      </if>
      <if test="vMoneytype != null">
        v_moneytype,
      </if>
      <if test="remark1 != null">
        remark1,
      </if>
      <if test="remark2 != null">
        remark2,
      </if>
    </trim>
    <trim prefix="values (" suffix=")" suffixOverrides=",">
      <if test="createUserId != null">
        #{createUserId,jdbcType=INTEGER},
      </if>
      <if test="createTime != null">
        #{createTime,jdbcType=TIMESTAMP},
      </if>
      <if test="type != null">
        #{type,jdbcType=TINYINT},
      </if>
      <if test="orderId != null">
        #{orderId,jdbcType=VARCHAR},
      </if>
      <if test="payState != null">
        #{payState,jdbcType=TINYINT},
      </if>
      <if test="endTime != null">
        #{endTime,jdbcType=TIMESTAMP},
      </if>
      <if test="totalFee != null">
        #{totalFee,jdbcType=DECIMAL},
      </if>
      <if test="vOid != null">
        #{vOid,jdbcType=VARCHAR},
      </if>
      <if test="vPmodeid != null">
        #{vPmodeid,jdbcType=VARCHAR},
      </if>
      <if test="vPmode != null">
        #{vPmode,jdbcType=VARCHAR},
      </if>
      <if test="vPstatus != null">
        #{vPstatus,jdbcType=VARCHAR},
      </if>
      <if test="vPstring != null">
        #{vPstring,jdbcType=VARCHAR},
      </if>
      <if test="vAmount != null">
        #{vAmount,jdbcType=VARCHAR},
      </if>
      <if test="vMoneytype != null">
        #{vMoneytype,jdbcType=VARCHAR},
      </if>
      <if test="remark1 != null">
        #{remark1,jdbcType=VARCHAR},
      </if>
      <if test="remark2 != null">
        #{remark2,jdbcType=VARCHAR},
      </if>
    </trim>
  </insert>
  <update id="updateByPrimaryKeySelective" parameterType="com.i9he.m2b.model.JDPay">
    <!--
      WARNING - @mbggenerated
      This element is automatically generated by MyBatis Generator, do not modify.
      copyright@ www.9he.com
    -->
    update b2b_pay_jdpay
    <set>
      <if test="createUserId != null">
        create_user_id = #{createUserId,jdbcType=INTEGER},
      </if>
      <if test="createTime != null">
        create_time = #{createTime,jdbcType=TIMESTAMP},
      </if>
      <if test="type != null">
        `type` = #{type,jdbcType=TINYINT},
      </if>
      <if test="orderId != null">
        order_id = #{orderId,jdbcType=VARCHAR},
      </if>
      <if test="payState != null">
        pay_state = #{payState,jdbcType=TINYINT},
      </if>
      <if test="endTime != null">
        end_time = #{endTime,jdbcType=TIMESTAMP},
      </if>
      <if test="totalFee != null">
        total_fee = #{totalFee,jdbcType=DECIMAL},
      </if>
      <if test="vOid != null">
        v_oid = #{vOid,jdbcType=VARCHAR},
      </if>
      <if test="vPmodeid != null">
        v_pmodeid = #{vPmodeid,jdbcType=VARCHAR},
      </if>
      <if test="vPmode != null">
        v_pmode = #{vPmode,jdbcType=VARCHAR},
      </if>
      <if test="vPstatus != null">
        v_pstatus = #{vPstatus,jdbcType=VARCHAR},
      </if>
      <if test="vPstring != null">
        v_pstring = #{vPstring,jdbcType=VARCHAR},
      </if>
      <if test="vAmount != null">
        v_amount = #{vAmount,jdbcType=VARCHAR},
      </if>
      <if test="vMoneytype != null">
        v_moneytype = #{vMoneytype,jdbcType=VARCHAR},
      </if>
      <if test="remark1 != null">
        remark1 = #{remark1,jdbcType=VARCHAR},
      </if>
      <if test="remark2 != null">
        remark2 = #{remark2,jdbcType=VARCHAR},
      </if>
    </set>
    where id = #{id,jdbcType=INTEGER}
  </update>
  <update id="updateByPrimaryKey" parameterType="com.i9he.m2b.model.JDPay">
    <!--
      WARNING - @mbggenerated
      This element is automatically generated by MyBatis Generator, do not modify.
      copyright@ www.9he.com
    -->
    update b2b_pay_jdpay
    set create_user_id = #{createUserId,jdbcType=INTEGER},
      create_time = #{createTime,jdbcType=TIMESTAMP},
      `type` = #{type,jdbcType=TINYINT},
      order_id = #{orderId,jdbcType=VARCHAR},
      pay_state = #{payState,jdbcType=TINYINT},
      end_time = #{endTime,jdbcType=TIMESTAMP},
      total_fee = #{totalFee,jdbcType=DECIMAL},
      v_oid = #{vOid,jdbcType=VARCHAR},
      v_pmodeid = #{vPmodeid,jdbcType=VARCHAR},
      v_pmode = #{vPmode,jdbcType=VARCHAR},
      v_pstatus = #{vPstatus,jdbcType=VARCHAR},
      v_pstring = #{vPstring,jdbcType=VARCHAR},
      v_amount = #{vAmount,jdbcType=VARCHAR},
      v_moneytype = #{vMoneytype,jdbcType=VARCHAR},
      remark1 = #{remark1,jdbcType=VARCHAR},
      remark2 = #{remark2,jdbcType=VARCHAR}
    where id = #{id,jdbcType=INTEGER}
  </update>
  
  <!-- selectByVoid -->
  <select id="selectByVoid" parameterType="java.lang.Integer" resultMap="BaseResultMap">
    select 
    <include refid="Base_Column_List" />
    from b2b_pay_jdpay
    where v_oid = #{v_oid}
  </select>
  
  <!-- selectByTypeOrderID -->
  <select id="selectByTypeOrderID" parameterType="java.lang.Integer" resultMap="BaseResultMap">
    select 
    <include refid="Base_Column_List" />
    from b2b_pay_jdpay
    where type = #{type} and order_id = #{orderID} and is_del = 0
    order by id desc limit 1
  </select>
</mapper>